README.rst
setup.py
aiohttp_prometheus/__init__.py
aiohttp_prometheus/middleware.py
aiohttp_prometheus/view.py
aiohttp_prometheus_client.egg-info/PKG-INFO
aiohttp_prometheus_client.egg-info/SOURCES.txt
aiohttp_prometheus_client.egg-info/dependency_links.txt
aiohttp_prometheus_client.egg-info/requires.txt
aiohttp_prometheus_client.egg-info/top_level.txt