Metadata-Version: 2.1
Name: aiohttp-prometheus-client
Version: 0.1.1
Summary: HTTP metrics for a aiohttp application
Home-page: https://github.com/RailYakup/aiohttp-prometheus.git
Author: Globo.com, Rail Yakup
Author-email: backstage@corp.globo.com, Rail1996@mail.ru
License: MIT
Download-URL: https://github.com/RailYakup/aiohttp-prometheus/archive/0.1.1.tar.gz
Keywords: prometheus,aiohttp
Platform: UNKNOWN
Classifier: Development Status :: 4 - Beta
Classifier: Intended Audience :: Developers
Classifier: License :: OSI Approved :: MIT License
Classifier: Natural Language :: English
Classifier: Operating System :: MacOS
Classifier: Operating System :: POSIX
Classifier: Operating System :: Unix
Classifier: Operating System :: OS Independent
Classifier: Programming Language :: Python :: 2.7
Classifier: Programming Language :: Python :: 3.5
Classifier: Programming Language :: Python :: 3.6
Classifier: Programming Language :: Python :: 3.7
Classifier: Programming Language :: Python :: 3.8
Provides-Extra: tests
